testing/__init__.py
testing/__main__.py
testing/utils.py
testing/assessments/__init__.py
testing/assessments/python_basic.py
edbsxkkpcelbrmkwfwnyq-0.5.0.dist-info/LICENSE
edbsxkkpcelbrmkwfwnyq-0.5.0.dist-info/METADATA
edbsxkkpcelbrmkwfwnyq-0.5.0.dist-info/WHEEL
edbsxkkpcelbrmkwfwnyq-0.5.0.dist-info/top_level.txt
edbsxkkpcelbrmkwfwnyq-0.5.0.dist-info/RECORD
