Metadata-Version: 2.1
Name: edbsxkkpcelbrmkwfwnyq
Version: 0.5.0
Summary: Unnamed repository; edit this file 'description' to name the repository.
Author: James Kabbes
Author-email: jameskabbes@gmail.com
Classifier: Programming Language :: Python :: 3
Classifier: License :: OSI Approved :: MIT License
Classifier: Operating System :: OS Independent
Requires-Python: >=3.7
License-File: LICENSE
